chromatic_tda/__init__.py
chromatic_tda/algorithms/__init__.py
chromatic_tda/algorithms/chromatic_subcomplex_utils.py
chromatic_tda/algorithms/legacy_radius_function_utils.py
chromatic_tda/algorithms/persistence_algorithm.py
chromatic_tda/algorithms/radius_function.py
chromatic_tda/algorithms/reduce_matrix.py
chromatic_tda/algorithms/test/__init__.py
chromatic_tda/algorithms/test/test_chromatic_subcomplex.py
chromatic_tda/algorithms/test/test_radius_function.py
chromatic_tda/core/__init__.py
chromatic_tda/core/chromatic_alpha_complex_factory.py
chromatic_tda/core/core_chromatic_alpha_complex.py
chromatic_tda/core/core_simplicial_complex.py
chromatic_tda/core/simplicial_complex_factory.py
chromatic_tda/core/stack.py
chromatic_tda/core/test/__init__.py
chromatic_tda/core/test/chromatic_alpha_complex_construction_test.py
chromatic_tda/core/test/test_data/chralph_integer_2_2.json
chromatic_tda/core/test/test_data/chralph_random_10_10.json
chromatic_tda/core/test/test_data/chralph_random_10_10_5.json
chromatic_tda/core/test/test_data/chralph_random_15_15.json
chromatic_tda/core/test/test_data/chralph_random_15_8_7.json
chromatic_tda/core/test/test_data/chralph_random_5_2_1.json
chromatic_tda/entities/__init__.py
chromatic_tda/entities/chromatic_alpha_complex.py
chromatic_tda/entities/simplicial_complex.py
chromatic_tda/entities/test/__init__.py
chromatic_tda/entities/test/simplicial_complex_construction_test.py
chromatic_tda/plots/__init__.py
chromatic_tda/plots/plotting_functions.py
chromatic_tda/tests/__init__.py
chromatic_tda/tests/test_bars.py
chromatic_tda/tests/test_data/line_sep.json
chromatic_tda/tests/test_data/one_circle_20_40.json
chromatic_tda/tests/test_data/one_circle_3col_back_split.json
chromatic_tda/tests/test_data/one_circle_3col_bi-circle_tri-filled.json
chromatic_tda/tests/test_data/one_circle_3col_circ_split.json
chromatic_tda/tests/test_data/random.json
chromatic_tda/tests/test_data/random2.json
chromatic_tda/tests/test_data/two_circles.json
chromatic_tda-1.1.7.dist-info/LICENSE.txt
chromatic_tda-1.1.7.dist-info/METADATA
chromatic_tda-1.1.7.dist-info/WHEEL
chromatic_tda-1.1.7.dist-info/RECORD
