Metadata-Version: 2.1
Name: chromatic_tda
Version: 1.1.7
Summary: Tool to compute six-packs of persistence diagrams for chromatic point clouds
Home-page: https://github.com/OnDraganov/chromatic-tda
License: AGPL-3.0-or-later
Keywords: tda,topological data analysis,chromatic,chromatic alpha,delaunay,persistence,persistent homology
Author: Ondrej Draganov
Author-email: ondrej.draganov@ist.ac.at
Requires-Python: >=3.10
Classifier: License :: OSI Approved :: GNU Affero General Public License v3 or later (AGPLv3+)
Classifier: Programming Language :: Python :: 3
Classifier: Programming Language :: Python :: 3.10
Classifier: Programming Language :: Python :: 3.11
Classifier: Programming Language :: Python :: 3.12
Requires-Dist: matplotlib (>=3.8.0)
Requires-Dist: mypy (>=1.3.0,<2.0.0)
Requires-Dist: numpy (>=2.1,<3.0)
Requires-Dist: pytest (>=8.1.1,<9.0.0)
Requires-Dist: scipy (>=1.14,<2.0)
Requires-Dist: typing_extensions (>=4.11.0,<5.0.0)
Project-URL: Documentation, https://github.com/OnDraganov/chromatic-tda
Project-URL: Repository, https://github.com/OnDraganov/chromatic-tda
